{"info": "clevr derendered scene", "scenes": [{"image_index": 0, "image_filename": "CLEVR_val_000000.png", "objects": [{"shape": "cylinder", "size": "large", "material": "rubber", "color": "blue", "position": [-2.0773723125457764, -1.69562566280365, 0.6943913102149963]}, {"shape": "cylinder", "size": "small", "material": "rubber", "color": "blue", "position": [0.3452800512313843, 0.7692211270332336, 0.35954102873802185]}, {"shape": "cube", "size": "small", "material": "metal", "color": "blue", "position": [1.584023356437683, 2.2449235916137695, 0.5376203060150146]}, {"shape": "cube", "size": "large", "material": "metal", "color": "blue", "position": [-0.729112982749939, -0.44984421133995056, 0.5515612363815308]}]}, {"image_index": 1, "image_filename": "CLEVR_val_000001.png", "objects": [{"shape": "cylinder", "size": "large", "material": "rubber", "color": "blue", "position": [-1.7522636651992798, -1.4774823188781738, 0.6890215277671814]}, {"shape": "cylinder", "size": "small", "material": "rubber", "color": "blue", "position": [0.5714006423950195, 0.9135094881057739, 0.360721617937088]}, {"shape": "cylinder", "size": "large", "material": "metal", "color": "blue", "position": [-0.5876370668411255, -0.262688010931015, 0.6843430399894714]}, {"shape": "cylinder", "size": "large", "material": "metal", "color": "blue", "position": [1.7577928304672241, 2.425555944442749, 0.5362339615821838]}]}, {"image_index": 2, "image_filename": "CLEVR_val_000002.png", "objects": [{"shape": "cylinder", "size": "large", "material": "rubber", "color": "blue", "position": [-0.8992162346839905, -2.4862923622131348, 0.665877103805542]}, {"shape": "cylinder", "size": "large", "material": "rubber", "color": "blue", "position": [1.4238934516906738, 0.16234561800956726, 0.5696749687194824]}, {"shape": "sphere", "size": "large", "material": "rubber", "color": "blue", "position": [0.19230332970619202, -0.981072187423706, 0.673253059387207]}, {"shape": "sphere", "size": "large", "material": "rubber", "color": "blue", "position": [2.5593955516815186, 1.5271356105804443, 0.5754548907279968]}]}, {"image_index": 3, "image_filename": "CLEVR_val_000003.png", "objects": [{"shape": "cylinder", "size": "large", "material": "rubber", "color": "blue", "position": [-1.5175011157989502, -2.2523255348205566, 0.6924014687538147]}, {"shape": "cube", "size": "large", "material": "metal", "color": "blue", "position": [2.052577495574951, 1.4381427764892578, 0.6079355478286743]}]}, {"image_index": 4, "image_filename": "CLEVR_val_000004.png", "objects": [{"shape": "cylinder", "size": "large", "material": "rubber", "color": "blue", "position": [-1.29371178150177, -2.421422243118286, 0.6929675936698914]}, {"shape": "cube", "size": "large", "material": "metal", "color": "blue", "position": [2.260857105255127, 1.4473406076431274, 0.6115169525146484]}]}, {"image_index": 5, "image_filename": "CLEVR_val_000005.png", "objects": [{"shape": "cube", "size": "large", "material": "rubber", "color": "blue", "position": [0.5878922343254089, 0.07974229753017426, 0.5476024150848389]}, {"shape": "cylinder", "size": "large", "material": "rubber", "color": "blue", "position": [-1.1870110034942627, -1.7486721277236938, 0.6834010481834412]}, {"shape": "cylinder", "size": "large", "material": "rubber", "color": "blue", "position": [2.4619534015655518, 1.9224337339401245, 0.5367212891578674]}]}, {"image_index": 6, "image_filename": "CLEVR_val_000006.png", "objects": [{"shape": "cylinder", "size": "large", "material": "rubber", "color": "blue", "position": [-1.7009526491165161, -1.5415897369384766, 0.6887513995170593]}, {"shape": "cylinder", "size": "large", "material": "rubber", "color": "blue", "position": [-0.5844535827636719, -0.33585870265960693, 0.6813104152679443]}, {"shape": "cube", "size": "small", "material": "metal", "color": "blue", "position": [0.6014831066131592, 0.7869241237640381, 0.4047248661518097]}, {"shape": "cube", "size": "small", "material": "metal", "color": "blue", "position": [1.7351716756820679, 2.1374924182891846, 0.38287389278411865]}]}, {"image_index": 7, "image_filename": "CLEVR_val_000007.png", "objects": []}, {"image_index": 8, "image_filename": "CLEVR_val_000008.png", "objects": []}, {"image_index": 9, "image_filename": "CLEVR_val_000009.png", "objects": []}, {"image_index": 10, "image_filename": "CLEVR_val_000010.png", "objects": []}]}