{"sorts": ["object", "label"], "predicates": {"left": ["object", "object"], "behind": ["object", "object"], "disequal": ["object", "object"], "has_label": ["object", "label"], "cyan": ["object"], "metal": ["object"], "large": ["object"], "same_color": ["object", "object"], "same_material": ["object", "object"], "same_size": ["object", "object"], "same_shape": ["object", "object"], "right": ["object", "object"], "front": ["object", "object"], "red": ["object"], "small": ["object"]}, "elements": {"object": ["4-0", "4-1", "4-2", "4-3"], "label": ["sphere", "cylinder"]}, "interpretation": {"left": [["4-1", "4-0"], ["4-2", "4-0"], ["4-3", "4-0"], ["4-1", "4-2"], ["4-1", "4-3"], ["4-2", "4-3"]], "behind": [["4-1", "4-0"], ["4-2", "4-0"], ["4-3", "4-0"], ["4-1", "4-2"], ["4-1", "4-3"], ["4-2", "4-3"]], "disequal": [["4-1", "4-0"], ["4-2", "4-0"], ["4-3", "4-0"], ["4-0", "4-1"], ["4-2", "4-1"], ["4-3", "4-1"], ["4-0", "4-2"], ["4-1", "4-2"], ["4-3", "4-2"], ["4-0", "4-3"], ["4-1", "4-3"], ["4-2", "4-3"]], "has_label": [["4-0", "cylinder"], ["4-1", "cylinder"], ["4-2", "cylinder"], ["4-3", "sphere"]], "cyan": [["4-0"], ["4-1"], ["4-2"]], "metal": [["4-0"], ["4-1"], ["4-2"], ["4-3"]], "large": [["4-0"], ["4-1"], ["4-2"]], "same_color": [["4-1", "4-0"], ["4-2", "4-0"], ["4-0", "4-1"], ["4-2", "4-1"], ["4-0", "4-2"], ["4-1", "4-2"]], "same_material": [["4-1", "4-0"], ["4-2", "4-0"], ["4-3", "4-0"], ["4-0", "4-1"], ["4-2", "4-1"], ["4-3", "4-1"], ["4-0", "4-2"], ["4-1", "4-2"], ["4-3", "4-2"], ["4-0", "4-3"], ["4-1", "4-3"], ["4-2", "4-3"]], "same_size": [["4-1", "4-0"], ["4-2", "4-0"], ["4-0", "4-1"], ["4-2", "4-1"], ["4-0", "4-2"], ["4-1", "4-2"]], "same_shape": [["4-1", "4-0"], ["4-2", "4-0"], ["4-0", "4-1"], ["4-2", "4-1"], ["4-0", "4-2"], ["4-1", "4-2"]], "right": [["4-0", "4-1"], ["4-2", "4-1"], ["4-3", "4-1"], ["4-0", "4-2"], ["4-3", "4-2"], ["4-0", "4-3"]], "front": [["4-0", "4-1"], ["4-2", "4-1"], ["4-3", "4-1"], ["4-0", "4-2"], ["4-3", "4-2"], ["4-0", "4-3"]], "red": [["4-3"]], "small": [["4-3"]]}, "raw": {"scene": [{"id": "4-0", "position": [1.7527180910110474, 1.5353962182998657, 0.6938053369522095], "color": "cyan", "material": "metal", "shape": "cylinder", "size": "large"}, {"id": "4-1", "position": [-1.4227453470230103, -2.122722864151001, 0.6963577270507812], "color": "cyan", "material": "metal", "shape": "cylinder", "size": "large"}, {"id": "4-2", "position": [-0.28027406334877014, -0.9216755032539368, 0.6909168362617493], "color": "cyan", "material": "metal", "shape": "cylinder", "size": "large"}, {"id": "4-3", "position": [0.7422447800636292, 0.21894726157188416, 0.34835612773895264], "color": "red", "material": "metal", "shape": "sphere", "size": "small"}]}}