{"sorts": ["object", "label"], "predicates": {"left": ["object", "object"], "behind": ["object", "object"], "disequal": ["object", "object"], "has_label": ["object", "label"], "purple": ["object"], "rubber": ["object"], "large": ["object"], "same_color": ["object", "object"], "same_material": ["object", "object"], "same_size": ["object", "object"], "same_shape": ["object", "object"], "right": ["object", "object"], "front": ["object", "object"], "metal": ["object"], "small": ["object"]}, "elements": {"object": ["4-0", "4-1", "4-2"], "label": ["cylinder", "sphere"]}, "interpretation": {"left": [["4-1", "4-0"], ["4-2", "4-0"], ["4-1", "4-2"]], "behind": [["4-1", "4-0"], ["4-2", "4-0"], ["4-1", "4-2"]], "disequal": [["4-1", "4-0"], ["4-2", "4-0"], ["4-0", "4-1"], ["4-2", "4-1"], ["4-0", "4-2"], ["4-1", "4-2"]], "has_label": [["4-0", "cylinder"], ["4-1", "cylinder"], ["4-2", "sphere"]], "purple": [["4-0"], ["4-1"], ["4-2"]], "rubber": [["4-0"], ["4-1"]], "large": [["4-0"], ["4-1"]], "same_color": [["4-1", "4-0"], ["4-2", "4-0"], ["4-0", "4-1"], ["4-2", "4-1"], ["4-0", "4-2"], ["4-1", "4-2"]], "same_material": [["4-1", "4-0"], ["4-0", "4-1"]], "same_size": [["4-1", "4-0"], ["4-0", "4-1"]], "same_shape": [["4-1", "4-0"], ["4-0", "4-1"]], "right": [["4-0", "4-1"], ["4-2", "4-1"], ["4-0", "4-2"]], "front": [["4-0", "4-1"], ["4-2", "4-1"], ["4-0", "4-2"]], "metal": [["4-2"]], "small": [["4-2"]]}, "raw": {"scene": [{"id": "4-0", "position": [1.8650752305984497, 1.84357488155365, 0.6844176054000854], "color": "purple", "material": "rubber", "shape": "cylinder", "size": "large"}, {"id": "4-1", "position": [-1.2351295948028564, -1.9400324821472168, 0.6935842633247375], "color": "purple", "material": "rubber", "shape": "cylinder", "size": "large"}, {"id": "4-2", "position": [0.6938746571540833, 0.5453421473503113, 0.3539980947971344], "color": "purple", "material": "metal", "shape": "sphere", "size": "small"}]}}