{"sorts": ["object", "label"], "predicates": {"right": ["object", "object"], "front": ["object", "object"], "disequal": ["object", "object"], "has_label": ["object", "label"], "brown": ["object"], "rubber": ["object"], "large": ["object"], "same_material": ["object", "object"], "same_size": ["object", "object"], "same_shape": ["object", "object"], "left": ["object", "object"], "behind": ["object", "object"], "gray": ["object"], "metal": ["object"], "small": ["object"], "purple": ["object"]}, "elements": {"object": ["4-0", "4-1", "4-2"], "label": ["sphere", "cylinder"]}, "interpretation": {"right": [["4-1", "4-0"], ["4-2", "4-0"], ["4-2", "4-1"]], "front": [["4-1", "4-0"], ["4-2", "4-0"], ["4-2", "4-1"]], "disequal": [["4-1", "4-0"], ["4-2", "4-0"], ["4-0", "4-1"], ["4-2", "4-1"], ["4-0", "4-2"], ["4-1", "4-2"]], "has_label": [["4-0", "cylinder"], ["4-1", "sphere"], ["4-2", "cylinder"]], "brown": [["4-0"]], "rubber": [["4-0"], ["4-2"]], "large": [["4-0"], ["4-2"]], "same_material": [["4-2", "4-0"], ["4-0", "4-2"]], "same_size": [["4-2", "4-0"], ["4-0", "4-2"]], "same_shape": [["4-2", "4-0"], ["4-0", "4-2"]], "left": [["4-0", "4-1"], ["4-0", "4-2"], ["4-1", "4-2"]], "behind": [["4-0", "4-1"], ["4-0", "4-2"], ["4-1", "4-2"]], "gray": [["4-1"]], "metal": [["4-1"]], "small": [["4-1"]], "purple": [["4-2"]]}, "raw": {"scene": [{"id": "4-0", "position": [-1.0155701637268066, -1.9531439542770386, 0.684356689453125], "color": "brown", "material": "rubber", "shape": "cylinder", "size": "large"}, {"id": "4-1", "position": [1.0329954624176025, 0.604385495185852, 0.3395511507987976], "color": "gray", "material": "metal", "shape": "sphere", "size": "small"}, {"id": "4-2", "position": [2.23762583732605, 1.9594672918319702, 0.6803025603294373], "color": "purple", "material": "rubber", "shape": "cylinder", "size": "large"}]}}