{"info": "clevr derendered scene", "scenes": [{"image_index": 0, "image_filename": "CLEVR_val_000000.png", "objects": [{"shape": "cube", "size": "large", "material": "metal", "color": "green", "position": [-2.5434722900390625, -1.4069504737854004, 0.6911511421203613]}, {"shape": "cylinder", "size": "large", "material": "rubber", "color": "yellow", "position": [0.659101128578186, 2.1747424602508545, 0.6755600571632385]}]}, {"image_index": 1, "image_filename": "CLEVR_val_000001.png", "objects": [{"shape": "sphere", "size": "large", "material": "metal", "color": "green", "position": [-1.2166366577148438, -1.4553223848342896, 0.6834706664085388]}, {"shape": "cylinder", "size": "large", "material": "rubber", "color": "yellow", "position": [1.8259438276290894, 2.2872791290283203, 0.6674631834030151]}]}, {"image_index": 2, "image_filename": "CLEVR_val_000002.png", "objects": [{"shape": "cube", "size": "large", "material": "rubber", "color": "green", "position": [-0.9716362357139587, -1.9089871644973755, 0.683303713798523]}, {"shape": "cylinder", "size": "large", "material": "rubber", "color": "yellow", "position": [2.410973072052002, 1.7730424404144287, 0.6667811870574951]}]}, {"image_index": 3, "image_filename": "CLEVR_val_000003.png", "objects": [{"shape": "cylinder", "size": "large", "material": "rubber", "color": "green", "position": [-0.20474547147750854, -0.3655572831630707, 0.6738126277923584]}, {"shape": "cylinder", "size": "large", "material": "rubber", "color": "green", "position": [1.58989679813385, 1.5069653987884521, 0.6721714735031128]}, {"shape": "cube", "size": "large", "material": "metal", "color": "yellow", "position": [-1.7561472654342651, -2.139247417449951, 0.6820590496063232]}]}, {"image_index": 4, "image_filename": "CLEVR_val_000004.png", "objects": [{"shape": "cylinder", "size": "large", "material": "rubber", "color": "gray", "position": [-0.8762202858924866, -0.3935096561908722, 0.6740163564682007]}, {"shape": "cylinder", "size": "large", "material": "rubber", "color": "gray", "position": [1.2968645095825195, 2.2500414848327637, 0.6712915897369385]}, {"shape": "cylinder", "size": "large", "material": "rubber", "color": "gray", "position": [0.1483958512544632, 0.8178987503051758, 0.672846794128418]}, {"shape": "cube", "size": "large", "material": "metal", "color": "gray", "position": [-1.9720317125320435, -1.6244354248046875, 0.6832090020179749]}]}, {"image_index": 5, "image_filename": "CLEVR_val_000005.png", "objects": [{"shape": "cube", "size": "large", "material": "metal", "color": "green", "position": [-1.6307910680770874, -2.372244358062744, 0.6847206354141235]}, {"shape": "cylinder", "size": "large", "material": "rubber", "color": "yellow", "position": [-0.5324090123176575, -1.1442723274230957, 0.6759829521179199]}, {"shape": "cylinder", "size": "large", "material": "rubber", "color": "yellow", "position": [1.657272219657898, 1.5006070137023926, 0.6736239194869995]}, {"shape": "cylinder", "size": "large", "material": "rubber", "color": "yellow", "position": [0.5897743701934814, 0.24099725484848022, 0.6708346605300903]}]}, {"image_index": 6, "image_filename": "CLEVR_val_000006.png", "objects": []}, {"image_index": 7, "image_filename": "CLEVR_val_000007.png", "objects": []}, {"image_index": 8, "image_filename": "CLEVR_val_000008.png", "objects": []}, {"image_index": 9, "image_filename": "CLEVR_val_000009.png", "objects": []}, {"image_index": 10, "image_filename": "CLEVR_val_000010.png", "objects": []}]}