{"info": "clevr derendered scene", "scenes": [{"image_index": 0, "image_filename": "CLEVR_val_000000.png", "objects": [{"shape": "cylinder", "size": "small", "material": "metal", "color": "brown", "position": [1.2526228427886963, 2.817319631576538, 0.45249122381210327]}, {"shape": "cylinder", "size": "large", "material": "metal", "color": "purple", "position": [-2.2763168811798096, -0.856574296951294, 0.6886530518531799]}]}, {"image_index": 1, "image_filename": "CLEVR_val_000001.png", "objects": [{"shape": "cylinder", "size": "large", "material": "metal", "color": "brown", "position": [-2.311267375946045, -1.467323660850525, 0.6942450404167175]}, {"shape": "cylinder", "size": "large", "material": "metal", "color": "purple", "position": [1.201153039932251, 2.138413429260254, 0.5768724679946899]}]}, {"image_index": 2, "image_filename": "CLEVR_val_000002.png", "objects": [{"shape": "cylinder", "size": "large", "material": "metal", "color": "brown", "position": [0.5938475131988525, -0.8043813109397888, 0.6842861175537109]}, {"shape": "cylinder", "size": "large", "material": "metal", "color": "brown", "position": [2.943464756011963, 1.568795084953308, 0.614180862903595]}, {"shape": "cylinder", "size": "small", "material": "metal", "color": "purple", "position": [1.7610020637512207, 0.37063613533973694, 0.4239542484283447]}, {"shape": "cylinder", "size": "large", "material": "metal", "color": "purple", "position": [-0.4827658534049988, -1.9880625009536743, 0.6969684362411499]}]}, {"image_index": 3, "image_filename": "CLEVR_val_000003.png", "objects": [{"shape": "cylinder", "size": "large", "material": "metal", "color": "brown", "position": [-0.27254125475883484, -0.16501572728157043, 0.6805399060249329]}, {"shape": "cylinder", "size": "large", "material": "metal", "color": "brown", "position": [2.0275349617004395, 2.316549062728882, 0.6171997785568237]}, {"shape": "cylinder", "size": "large", "material": "metal", "color": "purple", "position": [-1.5084537267684937, -1.475196123123169, 0.688378095626831]}, {"shape": "cylinder", "size": "small", "material": "metal", "color": "purple", "position": [0.999821126461029, 0.9680405855178833, 0.39547061920166016]}]}, {"image_index": 4, "image_filename": "CLEVR_val_000004.png", "objects": [{"shape": "cylinder", "size": "large", "material": "metal", "color": "brown", "position": [-1.1143382787704468, -0.6867550611495972, 0.686499834060669]}, {"shape": "cylinder", "size": "small", "material": "metal", "color": "brown", "position": [0.6577132344245911, 0.9754897952079773, 0.36983436346054077]}, {"shape": "cylinder", "size": "large", "material": "metal", "color": "purple", "position": [-1.935019850730896, -1.8973723649978638, 0.6762109398841858]}, {"shape": "cylinder", "size": "small", "material": "metal", "color": "purple", "position": [1.6263823509216309, 2.029972791671753, 0.5248944759368896]}, {"shape": "cylinder", "size": "large", "material": "metal", "color": "purple", "position": [-0.1636885106563568, 0.18852242827415466, 0.5947543978691101]}]}, {"image_index": 5, "image_filename": "CLEVR_val_000005.png", "objects": []}, {"image_index": 6, "image_filename": "CLEVR_val_000006.png", "objects": []}, {"image_index": 7, "image_filename": "CLEVR_val_000007.png", "objects": []}, {"image_index": 8, "image_filename": "CLEVR_val_000008.png", "objects": []}, {"image_index": 9, "image_filename": "CLEVR_val_000009.png", "objects": []}, {"image_index": 10, "image_filename": "CLEVR_val_000010.png", "objects": []}]}